{
  "$hash": "ec8900048e802112db47c2017c24c829bab36030",
  "$id": "aws-servicecatalog-portfolioshare.json",
  "additionalProperties": false,
  "createOnlyProperties": [
    "/properties/AcceptLanguage",
    "/properties/AccountId",
    "/properties/PortfolioId"
  ],
  "description": "Resource Type definition for AWS::ServiceCatalog::PortfolioShare",
  "primaryIdentifier": ["/properties/Id"],
  "properties": {
    "AcceptLanguage": { "type": "string" },
    "AccountId": { "type": "string" },
    "Id": { "type": "string" },
    "PortfolioId": { "type": "string" },
    "ShareTagOptions": { "type": "boolean" }
  },
  "readOnlyProperties": ["/properties/Id"],
  "required": ["AccountId", "PortfolioId"],
  "typeName": "AWS::ServiceCatalog::PortfolioShare"
}
